plaknit/__init__.py
plaknit/analysis.py
plaknit/classify.py
plaknit/classify_cli.py
plaknit/cli.py
plaknit/common.py
plaknit/geometry.py
plaknit/mosaic.py
plaknit/orders.py
plaknit/plaknit.py
plaknit/planner.py
plaknit-0.1.0.dist-info/licenses/LICENSE
plaknit-0.1.0.dist-info/METADATA
plaknit-0.1.0.dist-info/WHEEL
plaknit-0.1.0.dist-info/entry_points.txt
plaknit-0.1.0.dist-info/top_level.txt
plaknit-0.1.0.dist-info/RECORD
