Metadata-Version: 2.4
Name: plaknit
Version: 0.1.0
Summary: Processing Large-Scale PlanetScope Data
Author-email: Dryver Finch <dryver2206@gmail.com>
License: MIT License
Project-URL: Homepage, https://github.com/dzfinch/plaknit
Project-URL: Issues, https://github.com/dzfinch/plaknit/issues
Project-URL: Documentation, https://dzfinch.github.io/plaknit/
Keywords: plaknit
Classifier: Intended Audience :: Developers
Classifier: License :: OSI Approved :: MIT License
Classifier: Natural Language :: English
Classifier: Programming Language :: Python :: 3.8
Classifier: Programming Language :: Python :: 3.9
Classifier: Programming Language :: Python :: 3.10
Classifier: Programming Language :: Python :: 3.11
Classifier: Programming Language :: Python :: 3.12
Requires-Python: >=3.8
License-File: LICENSE
Requires-Dist: geopandas
Requires-Dist: joblib
Requires-Dist: numpy
Requires-Dist: planet
Requires-Dist: pystac-client
Requires-Dist: pytest
Requires-Dist: rasterio
Requires-Dist: requests
Requires-Dist: rich
Requires-Dist: scikit-learn
Provides-Extra: extra
Requires-Dist: pandas; extra == "extra"
Provides-Extra: all
Requires-Dist: pandas; extra == "all"
Dynamic: license-file
